bulk/__init__.py
bulk/__main__.py
bulk/_bokeh_utils.py
bulk/widgets.py
bulk/cli/__init__.py
bulk/cli/download.py
bulk/cli/image.py
bulk/cli/text.py
tests/__init__.py
bulk-0.4.2.dist-info/LICENSE
bulk-0.4.2.dist-info/METADATA
bulk-0.4.2.dist-info/WHEEL
bulk-0.4.2.dist-info/entry_points.txt
bulk-0.4.2.dist-info/top_level.txt
bulk-0.4.2.dist-info/RECORD
